odoo/addons/auth_oauth_autologin/README.rst
odoo/addons/auth_oauth_autologin/__init__.py
odoo/addons/auth_oauth_autologin/__manifest__.py
odoo/addons/auth_oauth_autologin/controllers/__init__.py
odoo/addons/auth_oauth_autologin/controllers/main.py
odoo/addons/auth_oauth_autologin/i18n/auth_oauth_autologin.pot
odoo/addons/auth_oauth_autologin/i18n/it.po
odoo/addons/auth_oauth_autologin/models/__init__.py
odoo/addons/auth_oauth_autologin/models/auth_oauth_provider.py
odoo/addons/auth_oauth_autologin/readme/CONFIGURE.md
odoo/addons/auth_oauth_autologin/readme/DESCRIPTION.md
odoo/addons/auth_oauth_autologin/readme/USAGE.md
odoo/addons/auth_oauth_autologin/static/description/icon.png
odoo/addons/auth_oauth_autologin/static/description/index.html
odoo/addons/auth_oauth_autologin/static/src/js/web_login.esm.js
odoo/addons/auth_oauth_autologin/views/assets.xml
odoo/addons/auth_oauth_autologin/views/auth_oauth_provider.xml
odoo_addon_auth_oauth_autologin-17.0.1.0.0.4.dist-info/METADATA
odoo_addon_auth_oauth_autologin-17.0.1.0.0.4.dist-info/WHEEL
odoo_addon_auth_oauth_autologin-17.0.1.0.0.4.dist-info/top_level.txt
odoo_addon_auth_oauth_autologin-17.0.1.0.0.4.dist-info/RECORD
